{
    "array": [
        {
            "exchanges": [
                "16",
                "16",
                "16",
                "16",
                "16",
                "16"
            ],
            "pairPaths": [
                "bg",
                "dg",
                "df",
                "ef",
                "ce",
                "bc"
            ],
            "path": [
                "B",
                "G",
                "D",
                "F",
                "E",
                "C",
                "B"
            ]
        },
        {
            "exchanges": [
                "16",
                "16",
                "16",
                "16",
                "16",
                "16"
            ],
            "pairPaths": [
                "bc",
                "ce",
                "ef",
                "df",
                "dg",
                "bg"
            ],
            "path": [
                "B",
                "C",
                "E",
                "F",
                "D",
                "G",
                "B"
            ]
        },
        {
            "exchanges": [
                "16",
                "16",
                "16",
                "16",
                "16",
                "16"
            ],
            "pairPaths": [
                "bg",
                "dg",
                "df",
                "ef",
                "ce",
                "bc2"
            ],
            "path": [
                "B",
                "C",
                "E",
                "F",
                "D",
                "G",
                "B"
            ]
        },
        {
            "exchanges": [
                "16",
                "16",
                "16",
                "16",
                "16",
                "16"
            ],
            "pairPaths": [
                "bc2",
                "ce",
                "ef",
                "df",
                "dg",
                "bg"
            ],
            "path": [
                "B",
                "G",
                "D",
                "F",
                "E",
                "C",
                "B"
            ]
        },
        {
            "exchanges": [
                "16",
                "16",
                "16",
                "16"
            ],
            "pairPaths": [
                "bg",
                "dg",
                "cd",
                "bc"
            ],
            "path": [
                "B",
                "G",
                "D",
                "C",
                "B"
            ]
        },
        {
            "exchanges": [
                "16",
                "16",
                "16",
                "16"
            ],
            "pairPaths": [
                "bc",
                "cd",
                "dg",
                "bg"
            ],
            "path": [
                "B",
                "C",
                "D",
                "G",
                "B"
            ]
        },
        {
            "exchanges": [
                "16",
                "16",
                "16",
                "16"
            ],
            "pairPaths": [
                "bg",
                "dg",
                "cd",
                "bc2"
            ],
            "path": [
                "B",
                "C",
                "D",
                "G",
                "B"
            ]
        },
        {
            "exchanges": [
                "16",
                "16",
                "16",
                "16"
            ],
            "pairPaths": [
                "bc2",
                "cd",
                "dg",
                "bg"
            ],
            "path": [
                "B",
                "G",
                "D",
                "C",
                "B"
            ]
        }
    ]
}
